LICENSE
MANIFEST.in
README.md
setup.py
updoc/__init__.py
updoc/admin.py
updoc/context_processors.py
updoc/defaults.py
updoc/docset.py
updoc/extensions.py
updoc/feeds.py
updoc/forms.py
updoc/indexation.py
updoc/iniconf.py
updoc/middleware.py
updoc/models.py
updoc/process.py
updoc/root_urls.py
updoc/signals.py
updoc/urls.py
updoc/utils.py
updoc/views.py
updoc.egg-info/PKG-INFO
updoc.egg-info/SOURCES.txt
updoc.egg-info/dependency_links.txt
updoc.egg-info/entry_points.txt
updoc.egg-info/not-zip-safe
updoc.egg-info/requires.txt
updoc.egg-info/top_level.txt
updoc/__pycache__/__init__.cpython-36.pyc
updoc/__pycache__/admin.cpython-36.pyc
updoc/__pycache__/context_processors.cpython-36.pyc
updoc/__pycache__/defaults.cpython-36.pyc
updoc/__pycache__/docset.cpython-36.pyc
updoc/__pycache__/extensions.cpython-36.pyc
updoc/__pycache__/feeds.cpython-36.pyc
updoc/__pycache__/forms.cpython-36.pyc
updoc/__pycache__/indexation.cpython-36.pyc
updoc/__pycache__/iniconf.cpython-36.pyc
updoc/__pycache__/models.cpython-36.pyc
updoc/__pycache__/process.cpython-36.pyc
updoc/__pycache__/root_urls.cpython-36.pyc
updoc/__pycache__/signals.cpython-36.pyc
updoc/__pycache__/urls.cpython-36.pyc
updoc/__pycache__/utils.cpython-36.pyc
updoc/__pycache__/views.cpython-36.pyc
updoc/gravatar/__init__.py
updoc/gravatar/models.py
updoc/gravatar/urls.py
updoc/gravatar/views.py
updoc/locale/fr_FR/LC_MESSAGES/django.mo
updoc/locale/fr_FR/LC_MESSAGES/django.po
updoc/locale/fr_FR/LC_MESSAGES/updoc.mo
updoc/locale/fr_FR/LC_MESSAGES/updoc.po
updoc/management/__init__.py
updoc/management/__pycache__/__init__.cpython-36.pyc
updoc/management/commands/__init__.py
updoc/management/commands/addpackage.py
updoc/management/commands/deployment.py
updoc/management/commands/init_es.py
updoc/migrations/0001_initial.py
updoc/migrations/0002_uploaddoc_version.py
updoc/migrations/__init__.py
updoc/migrations/__pycache__/0001_initial.cpython-36.pyc
updoc/migrations/__pycache__/0002_uploaddoc_version.cpython-36.pyc
updoc/migrations/__pycache__/__init__.cpython-36.pyc
updoc/progress/__init__.py
updoc/progress/compat.py
updoc/progress/progressbar.py
updoc/progress/widgets.py
updoc/static/css/fuelux.min.css
